[
  {
    "id": 1,
    "name": "Code & Coffee",
    "address": "123 Tech Street, San Francisco, CA 94105",
    "type": "Cafe",
    "dietaryOptions": {
      "glutenFree": true,
      "vegan": true,
      "vegetarian": true,
      "dairyFree": true,
      "nutFree": false
    },
    "price": "$$",
    "cuisine": "Coffee & Pastries",
    "rating": 5,
    "comment": "Amazing oat milk lattes and gluten-free pastries. Great WiFi for coding sessions!",
    "images": [],
    "createdAt": "2024-01-15T10:00:00Z",
    "createdBy": "dev_user"
  },
  {
    "id": 2,
    "name": "Bug Buster Bistro",
    "address": "456 Debug Avenue, San Francisco, CA 94105",
    "type": "Restaurant",
    "dietaryOptions": {
      "glutenFree": false,
      "vegan": false,
      "vegetarian": true,
      "dairyFree": false,
      "nutFree": true
    },
    "price": "$$$",
    "cuisine": "American",
    "rating": 4,
    "comment": "Great burgers and fries. Perfect for celebrating after fixing a tough bug!",
    "images": [],
    "createdAt": "2024-01-16T12:00:00Z",
    "createdBy": "hackathon_hacker"
  },
  {
    "id": 3,
    "name": "Stack Overflow Sushi",
    "address": "789 Algorithm Way, San Francisco, CA 94105",
    "type": "Sushi Bar",
    "dietaryOptions": {
      "glutenFree": true,
      "vegan": true,
      "vegetarian": true,
      "dairyFree": true,
      "nutFree": true
    },
    "price": "$$",
    "cuisine": "Japanese",
    "rating": 5,
    "comment": "Fresh sushi and amazing ramen. Named after the famous programming Q&A site!",
    "images": [],
    "createdAt": "2024-01-17T18:00:00Z",
    "createdBy": "foodie_coder"
  },
  {
    "id": 4,
    "name": "test eatery",
    "address": "hello",
    "type": "Ice Cream Shop",
    "dietaryOptions": {
      "glutenFree": true,
      "vegan": true,
      "vegetarian": false,
      "dairyFree": true,
      "nutFree": false
    },
    "price": "$$$$",
    "cuisine": "Mexican",
    "rating": 4,
    "comment": "good great place",
    "images": [],
    "createdAt": "2025-08-19T23:44:54.972Z",
    "createdBy": "current_user"
  }
]